tgtqdm/__init__.py
tgtqdm/logger.py
tgtqdm/progress.py
tgtqdm-0.0.1.dist-info/METADATA
tgtqdm-0.0.1.dist-info/WHEEL
tgtqdm-0.0.1.dist-info/top_level.txt
tgtqdm-0.0.1.dist-info/RECORD
