Metadata-Version: 2.1
Name: tgtqdm
Version: 0.0.1
Summary: watch your scripts go brr on telegram
Home-page: https://github.com/mayukhdeb/tgtqdm
Author: a very bored mayukh on a sunday night
Author-email: 
Classifier: Operating System :: OS Independent
